cog3pio-0.0.1.dist-info/METADATA
cog3pio-0.0.1.dist-info/WHEEL
cog3pio-0.0.1.dist-info/entry_points.txt
cog3pio-0.0.1.dist-info/licenses/LICENSE-APACHE
cog3pio-0.0.1.dist-info/licenses/LICENSE-MIT
cog3pio/__init__.py
cog3pio/cog3pio.cpython-313t-powerpc64le-linux-gnu.so
cog3pio/xarray_backend.py
cog3pio-0.0.1.dist-info/RECORD
