Metadata-Version: 2.4
Name: cog3pio
Version: 0.0.1
Classifier: Development Status :: 4 - Beta
Classifier: Intended Audience :: Science/Research
Classifier: Topic :: Scientific/Engineering
Classifier: Topic :: Software Development :: Libraries
Classifier: Operating System :: MacOS
Classifier: Operating System :: Microsoft :: Windows
Classifier: Operating System :: POSIX
Classifier: Operating System :: Unix
Classifier: Programming Language :: Rust
Classifier: Programming Language :: Python :: Free Threading
Classifier: Programming Language :: Python :: Implementation :: CPython
Requires-Dist: numpy>=2.0
Requires-Dist: xarray>=2023.12.0
Requires-Dist: pytest-codspeed ; extra == 'benchmark'
Requires-Dist: rioxarray ; extra == 'benchmark'
Requires-Dist: jupyter-book>=2.0.0a0 ; extra == 'docs'
Requires-Dist: myst-parser ; extra == 'docs'
Requires-Dist: sphinx ; extra == 'docs'
Requires-Dist: sphinx-ext-mystmd ; extra == 'docs'
Requires-Dist: pytest ; extra == 'tests'
Provides-Extra: benchmark
Provides-Extra: docs
Provides-Extra: tests
License-File: LICENSE-MIT
License-File: LICENSE-APACHE
Author: Wei Ji <23487320+weiji14@users.noreply.github.com>
Author-email: Wei Ji <23487320+weiji14@users.noreply.github.com>
License: MIT OR Apache-2.0
Requires-Python: >=3.12
